.gitignore
setup.cfg
setup.py
CyberQInterface.egg-info/PKG-INFO
CyberQInterface.egg-info/SOURCES.txt
CyberQInterface.egg-info/dependency_links.txt
CyberQInterface.egg-info/requires.txt
CyberQInterface.egg-info/top_level.txt
cyberqinterface/__init__.py
cyberqinterface/cyberqinterface.py
cyberqinterface/cyberqinterface_exceptions.py