Metadata-Version: 1.0
Name: CyberQInterface
Version: 1.0
Summary: Package of interface tools for the BBQGuru CyberQ Pit Temperature Controller
Home-page: https://github.com/thebrilliantidea/CyberQInterface
Author: Bryan Kemp
Author-email: bryan@thebrilliantidea.com
License: BSD New
Keywords: cyberq api bbq bbqguru
Platform: UNKNOWN
